newclear/__init__.py
newclear/cli_generator.py
newclear/command_generator.py
newclear/group_generator.py
newclear/main.py
newclear-0.1.0.dist-info/entry_points.txt
newclear-0.1.0.dist-info/WHEEL
newclear-0.1.0.dist-info/METADATA
newclear-0.1.0.dist-info/RECORD
